inscopix_cnmfe.cpython-310-x86_64-linux-gnu.so
inscopix_cnmfe-1.0.2.dist-info/LICENSE
inscopix_cnmfe-1.0.2.dist-info/METADATA
inscopix_cnmfe-1.0.2.dist-info/WHEEL
inscopix_cnmfe-1.0.2.dist-info/top_level.txt
inscopix_cnmfe-1.0.2.dist-info/RECORD
