Metadata-Version: 2.1
Name: inscopix-cnmfe
Version: 1.0.2
Summary: Inscopix CNMF-E for automated source extraction
Home-page: https://github.com/inscopix/isx-cnmfe
Author: Inscopix, Inc.
Author-email: support@inscopix.com
License: GNU AFFERO GENERAL PUBLIC LICENSE
Platform: Mac OS-X
Platform: Linux
Platform: Windows
Classifier: Operating System :: MacOS
Classifier: Operating System :: POSIX :: Linux
Classifier: Operating System :: Microsoft :: Windows
Classifier: Programming Language :: Python
Classifier: Programming Language :: Python :: 3
Classifier: License :: OSI Approved :: GNU Affero General Public License v3
Requires-Python: >=3.6
License-File: LICENSE
Requires-Dist: numpy (>=1.12.0)
